src/__init__.py
src/main.py
src/transform_pytest_report.py
test/TestTransformer.py
test/__init__.py
astronuts_python_reporter-0.0.4.dist-info/LICENSE
astronuts_python_reporter-0.0.4.dist-info/METADATA
astronuts_python_reporter-0.0.4.dist-info/WHEEL
astronuts_python_reporter-0.0.4.dist-info/entry_points.txt
astronuts_python_reporter-0.0.4.dist-info/top_level.txt
astronuts_python_reporter-0.0.4.dist-info/RECORD
