Metadata-Version: 2.1
Name: astronuts-python-reporter
Version: 0.0.4
Summary: A package to automate running pytest and transforming reports.
Home-page: https://github.com/astronuts-app/astronuts-python-reporter
Author: astronuts
License: UNKNOWN
Platform: UNKNOWN
License-File: LICENSE
Requires-Dist: pytest
